Workbook
Name T_EQUIPO: Listas!$A$2:$A$5
Name L_YNC: Listas!$N$2:$N$4
Name L_FUN: Listas!$O$2:$O$4
Name L_FALLAP: Listas!$P$2:$P$12
Name L_DESDE: Listas!$Q$2:$Q$8
Name L_PERM: Listas!$R$2:$R$4
Name L_ENC: Listas!$S$2:$S$5
Name L_OTRAF: Listas!$T$2:$T$10
Name L_LUZ: Listas!$U$2:$U$8
Name L_SENAL: Listas!$V$2:$V$6
Name L_AUTON: Listas!$W$2:$W$7
Name L_ZONAC: Listas!$X$2:$X$7
Name L_MANT: Listas!$Y$2:$Y$6
Name L_ABCE: Listas!$Z$2:$Z$4
Name L_ZONAI: Listas!$AA$2:$AA$9
Name L_ERR: Listas!$AB$2:$AB$7
Name L_PROG: Listas!$AC$2:$AC$8
Name L_SO: Listas!$AD$2:$AD$7
Name L_TEL: Listas!$AE$2:$AE$4
Name L_JUE: Listas!$AF$2:$AF$5
Name L_NCTRL: Listas!$AG$2:$AG$5
Name L_SOL: Listas!$AH$2:$AH$8
Name L_DANO: Listas!$AI$2:$AI$8
Name L_CUANDO: Listas!$AJ$2:$AJ$6
Name L_MOM: Listas!$AK$2:$AK$5
Name L_LIQ: Listas!$AL$2:$AL$8
Name L_E_PANT: Listas!$AM$2:$AM$5
Name L_E_CARC: Listas!$AN$2:$AN$5
Name L_PIN: Listas!$AO$2:$AO$5
Name L_ANTIG: Listas!$AP$2:$AP$7
Name L_USO: Listas!$AQ$2:$AQ$5
Name L_URG: Listas!$AR$2:$AR$5
Name L_CONT: Listas!$AS$2:$AS$5
Name L_BATED: Listas!$AT$2:$AT$6
Name L_CANT: Listas!$AU$2:$AU$6
Name L_CAID: Listas!$AV$2:$AV$4
Name L_DISCO: Listas!$AW$2:$AW$4
Name L_BATNIV: Listas!$AX$2:$AX$6
Name L_YN: Listas!$AY$2:$AY$3
Name L_YNS: Listas!$AZ$2:$AZ$4
Name L_TXT: Listas!$BA$2:$BA$2

Sheet Instrucciones
B1: RCP · Checklist de Recepción Técnica
B3: LISTAS DESPLEGABLES DEPENDIENTES
B4: Paso 1 · Equipo | C4: En «Recepción» elija Celular, Reloj, Computadora o Consola.
B5: Paso 2 · Categoría | C5: En cada fila, la lista «Categoría / Falla» muestra solo las categorías de ese equipo (datos generales, fallas, verificación, accesorios, fotos, pruebas, autorizaciones).
B6: Paso 3 · Pregunta | C6: La lista «Pregunta» muestra solo las preguntas de esa categoría para ese equipo.
B7: Paso 4 · Respuesta | C7: La lista «Respuesta» muestra solo las respuestas posibles de esa pregunta (Sí/No/No sé, fechas, tipos, estados…). Solo la contraseña se escribe.
B8: Varias preguntas | C8: Use una fila por pregunta (hay 100 filas). Si cambia el equipo o la categoría de una fila ya llenada, aparece «⚠ revisar»: vuelva a elegir esa fila.
B9: Colores y alertas | C9: Sí / Funciona en verde, No / No funciona en rojo, No sé / No probado en amarillo. Arriba salen alertas rojas (líquido, batería inflada, datos sin respaldo, reparación previa, golpe) y el nivel de atención.
B10: Guardar | C10: Por cada cliente use «Guardar como» con nombre nuevo y deje esta versión como plantilla limpia.
B11: PERSONALIZAR
B12: Hoja Preguntas | C12: Es una tabla: Equipo, Categoría, Pregunta y Tipo de respuesta. De ahí salen las listas. Para agregar una pregunta inserte una fila dentro del grupo de su equipo y categoría, llénela y copie las columnas E y F de la fila de arriba. Aparece sola en el desplegable.
B13: Hoja Listas | C13: Contiene los equipos, las categorías y las opciones de respuesta. Puede agregar opciones al final de cada lista.
B14: Importante | C14: Abra el archivo en Excel. Las vistas previas de celular o navegador no muestran las listas dependientes.

Sheet Recepción
B1: RCP · CHECKLIST DE RECEPCIÓN TÉCNICA
B2: Elija el equipo → la categoría o falla → la pregunta → la respuesta. Cada lista depende de la anterior.
B4: DATOS DEL EQUIPO Y DEL CLIENTE
B5: Tipo de equipo *
B6: N.º de orden
B7: Cliente
B8: Teléfono / WhatsApp
B9: Marca / Modelo
B10: Serial / IMEI
B11: Recibido por
B12: Fecha de recepción
B14: Nivel de atención | D14: =IF(D5="","",IF(OR(COUNTIFS($D$22:$D$121,"¿Ha tenido contacto con agua, humedad o algún líquido?",$E$22:$E$121,"Sí")>0,SUMPRODUCT(ISNUMBER(SEARCH("inflada",$D$22:$D$121))*($E$22:$E$121="Sí"))>0),"ALTA PRIORIDAD","Normal"))
B15: =IF(D5="","Paso 1: elija el tipo de equipo.","Preguntas respondidas: "&COUNTA(E22:E121)&" de "&COUNTA(D22:D121))
B16: =IF(COUNTIFS($D$22:$D$121,"¿Ha tenido contacto con agua, humedad o algún líquido?",$E$22:$E$121,"Sí")>0,"ALTA PRIORIDAD · Ingresa por CONTAMINACIÓN DE LÍQUIDO: registrarlo en la orden; no encender ni conectar al cargador.","")
B17: =IF(SUMPRODUCT(ISNUMBER(SEARCH("inflada",$D$22:$D$121))*($E$22:$E$121="Sí"))>0,"ALTA PRIORIDAD · Batería inflada / equipo deformado: riesgo de seguridad, manipular con cuidado y aislar el equipo.","")
B18: =IF(AND(COUNTIFS($D$22:$D$121,"¿Tiene información importante que no puede perder?",$E$22:$E$121,"Sí")>0,COUNTIFS($D$22:$D$121,"¿Tiene respaldo reciente de su información?",$E$22:$E$121,"Sí")=0),"DATOS EN RIESGO · Información importante SIN respaldo confirmado: reforzar la autorización antes de intervenir.","")
B19: =IF(COUNTIFS($D$22:$D$121,"¿Ha sido abierto o reparado anteriormente?",$E$22:$E$121,"Sí")>0,"Equipo abierto o reparado antes: fotografiar señales de apertura y anotar quién lo intervino.","")
B20: =IF(COUNTIFS($D$22:$D$121,"¿Sufrió algún golpe o caída recientemente?",$E$22:$E$121,"Sí")>0,"Golpe o caída reportado: documentar la zona del impacto y fotografiar daños existentes.","")
B21: N.º | C21: ① Categoría / Falla | D21: ② Pregunta | E21: ③ Respuesta | F21: Observación (opcional)
B22: 1 | G22: =IF(AND(D22<>"",I22=""),"⚠ revisar","") | H22: =IF(OR($D$5="",C22=""),"",$D$5&"|"&C22) | I22: =IF(OR(H22="",D22=""),"",IFERROR(MATCH(H22&"|"&D22,Preguntas!$F$2:$F$1000,0),"")) | K22: =IF(I22="","",INDEX(Preguntas!$D$2:$D$1000,I22)) | L22: =IF(K22="","L_YN","L_"&K22)
B23: 2 | G23: =IF(AND(D23<>"",I23=""),"⚠ revisar","") | H23: =IF(OR($D$5="",C23=""),"",$D$5&"|"&C23) | I23: =IF(OR(H23="",D23=""),"",IFERROR(MATCH(H23&"|"&D23,Preguntas!$F$2:$F$1000,0),"")) | K23: =IF(I23="","",INDEX(Preguntas!$D$2:$D$1000,I23)) | L23: =IF(K23="","L_YN","L_"&K23)
B24: 3 | G24: =IF(AND(D24<>"",I24=""),"⚠ revisar","") | H24: =IF(OR($D$5="",C24=""),"",$D$5&"|"&C24) | I24: =IF(OR(H24="",D24=""),"",IFERROR(MATCH(H24&"|"&D24,Preguntas!$F$2:$F$1000,0),"")) | K24: =IF(I24="","",INDEX(Preguntas!$D$2:$D$1000,I24)) | L24: =IF(K24="","L_YN","L_"&K24)
B25: 4 | G25: =IF(AND(D25<>"",I25=""),"⚠ revisar","") | H25: =IF(OR($D$5="",C25=""),"",$D$5&"|"&C25) | I25: =IF(OR(H25="",D25=""),"",IFERROR(MATCH(H25&"|"&D25,Preguntas!$F$2:$F$1000,0),"")) | K25: =IF(I25="","",INDEX(Preguntas!$D$2:$D$1000,I25)) | L25: =IF(K25="","L_YN","L_"&K25)
B26: 5 | G26: =IF(AND(D26<>"",I26=""),"⚠ revisar","") | H26: =IF(OR($D$5="",C26=""),"",$D$5&"|"&C26) | I26: =IF(OR(H26="",D26=""),"",IFERROR(MATCH(H26&"|"&D26,Preguntas!$F$2:$F$1000,0),"")) | K26: =IF(I26="","",INDEX(Preguntas!$D$2:$D$1000,I26)) | L26: =IF(K26="","L_YN","L_"&K26)
B27: 6 | G27: =IF(AND(D27<>"",I27=""),"⚠ revisar","") | H27: =IF(OR($D$5="",C27=""),"",$D$5&"|"&C27) | I27: =IF(OR(H27="",D27=""),"",IFERROR(MATCH(H27&"|"&D27,Preguntas!$F$2:$F$1000,0),"")) | K27: =IF(I27="","",INDEX(Preguntas!$D$2:$D$1000,I27)) | L27: =IF(K27="","L_YN","L_"&K27)
B28: 7 | G28: =IF(AND(D28<>"",I28=""),"⚠ revisar","") | H28: =IF(OR($D$5="",C28=""),"",$D$5&"|"&C28) | I28: =IF(OR(H28="",D28=""),"",IFERROR(MATCH(H28&"|"&D28,Preguntas!$F$2:$F$1000,0),"")) | K28: =IF(I28="","",INDEX(Preguntas!$D$2:$D$1000,I28)) | L28: =IF(K28="","L_YN","L_"&K28)
B29: 8 | G29: =IF(AND(D29<>"",I29=""),"⚠ revisar","") | H29: =IF(OR($D$5="",C29=""),"",$D$5&"|"&C29) | I29: =IF(OR(H29="",D29=""),"",IFERROR(MATCH(H29&"|"&D29,Preguntas!$F$2:$F$1000,0),"")) | K29: =IF(I29="","",INDEX(Preguntas!$D$2:$D$1000,I29)) | L29: =IF(K29="","L_YN","L_"&K29)
B30: 9 | G30: =IF(AND(D30<>"",I30=""),"⚠ revisar","") | H30: =IF(OR($D$5="",C30=""),"",$D$5&"|"&C30) | I30: =IF(OR(H30="",D30=""),"",IFERROR(MATCH(H30&"|"&D30,Preguntas!$F$2:$F$1000,0),"")) | K30: =IF(I30="","",INDEX(Preguntas!$D$2:$D$1000,I30)) | L30: =IF(K30="","L_YN","L_"&K30)
B31: 10 | G31: =IF(AND(D31<>"",I31=""),"⚠ revisar","") | H31: =IF(OR($D$5="",C31=""),"",$D$5&"|"&C31) | I31: =IF(OR(H31="",D31=""),"",IFERROR(MATCH(H31&"|"&D31,Preguntas!$F$2:$F$1000,0),"")) | K31: =IF(I31="","",INDEX(Preguntas!$D$2:$D$1000,I31)) | L31: =IF(K31="","L_YN","L_"&K31)
B32: 11 | G32: =IF(AND(D32<>"",I32=""),"⚠ revisar","") | H32: =IF(OR($D$5="",C32=""),"",$D$5&"|"&C32) | I32: =IF(OR(H32="",D32=""),"",IFERROR(MATCH(H32&"|"&D32,Preguntas!$F$2:$F$1000,0),"")) | K32: =IF(I32="","",INDEX(Preguntas!$D$2:$D$1000,I32)) | L32: =IF(K32="","L_YN","L_"&K32)
B33: 12 | G33: =IF(AND(D33<>"",I33=""),"⚠ revisar","") | H33: =IF(OR($D$5="",C33=""),"",$D$5&"|"&C33) | I33: =IF(OR(H33="",D33=""),"",IFERROR(MATCH(H33&"|"&D33,Preguntas!$F$2:$F$1000,0),"")) | K33: =IF(I33="","",INDEX(Preguntas!$D$2:$D$1000,I33)) | L33: =IF(K33="","L_YN","L_"&K33)
... B121: 100 | G121: =IF(AND(D121<>"",I121=""),"⚠ revisar","") | H121: =IF(OR($D$5="",C121=""),"",$D$5&"|"&C121) | I121: =IF(OR(H121="",D121=""),"",IFERROR(MATCH(H121&"|"&D121,Preguntas!$F$2:$F$1000,0),"")) | K121: =IF(I121="","",INDEX(Preguntas!$D$2:$D$1000,I121)) | L121: =IF(K121="","L_YN","L_"&K121)

Sheet Preguntas
A1: Equipo | B1: Categoría / Falla | C1: Pregunta | D1: Tipo de respuesta | E1: Clave (auto) | F1: Clave 2 (auto) | H1: Cómo agregar una pregunta: inserte una fila DENTRO del grupo de su equipo y categoría (clic derecho > Insertar), escriba Equipo, Categoría, Pregunta y Tipo de respuesta, y copie las columnas E y F de la fila de arriba. Tipo: YN, YNS, YNC, FUN u otra lista de la hoja Listas (sin «L_»).
A2: Celular | B2: Datos generales | C2: ¿Cuál es la falla principal que presenta el equipo? | D2: FALLAP | E2: =IF(OR(A2="",B2=""),"",A2&"|"&B2) | F2: =IF(OR(E2="",C2=""),"",E2&"|"&C2)
A3: Celular | B3: Datos generales | C3: ¿Desde cuándo presenta la falla? | D3: DESDE | E3: =IF(OR(A3="",B3=""),"",A3&"|"&B3) | F3: =IF(OR(E3="",C3=""),"",E3&"|"&C3)
A4: Celular | B4: Datos generales | C4: ¿La falla es permanente o sucede algunas veces? | D4: PERM | E4: =IF(OR(A4="",B4=""),"",A4&"|"&B4) | F4: =IF(OR(E4="",C4=""),"",E4&"|"&C4)
A5: Celular | B5: Datos generales | C5: ¿Sufrió algún golpe o caída recientemente? | D5: YNS | E5: =IF(OR(A5="",B5=""),"",A5&"|"&B5) | F5: =IF(OR(E5="",C5=""),"",E5&"|"&C5)
A6: Celular | B6: Datos generales | C6: ¿Ha tenido contacto con agua, humedad o algún líquido? | D6: YNS | E6: =IF(OR(A6="",B6=""),"",A6&"|"&B6) | F6: =IF(OR(E6="",C6=""),"",E6&"|"&C6)
A7: Celular | B7: Datos generales | C7: ¿Ha sido abierto o reparado anteriormente? | D7: YNS | E7: =IF(OR(A7="",B7=""),"",A7&"|"&B7) | F7: =IF(OR(E7="",C7=""),"",E7&"|"&C7)
A8: Celular | B8: Datos generales | C8: ¿Enciende actualmente? | D8: ENC | E8: =IF(OR(A8="",B8=""),"",A8&"|"&B8) | F8: =IF(OR(E8="",C8=""),"",E8&"|"&C8)
A9: Celular | B9: Datos generales | C9: ¿El equipo se reinicia o se apaga solo? | D9: YNS | E9: =IF(OR(A9="",B9=""),"",A9&"|"&B9) | F9: =IF(OR(E9="",C9=""),"",E9&"|"&C9)
A10: Celular | B10: Datos generales | C10: ¿Tiene información importante que no puede perder? | D10: YNS | E10: =IF(OR(A10="",B10=""),"",A10&"|"&B10) | F10: =IF(OR(E10="",C10=""),"",E10&"|"&C10)
A11: Celular | B11: Datos generales | C11: ¿Tiene respaldo reciente de su información? | D11: YNS | E11: =IF(OR(A11="",B11=""),"",A11&"|"&B11) | F11: =IF(OR(E11="",C11=""),"",E11&"|"&C11)
A12: Celular | B12: Datos generales | C12: ¿Hay alguna otra falla o condición que debamos conocer? | D12: OTRAF | E12: =IF(OR(A12="",B12=""),"",A12&"|"&B12) | F12: =IF(OR(E12="",C12=""),"",E12&"|"&C12)
A13: Celular | B13: Datos generales | C13: ¿Es la primera vez que presenta esta falla? | D13: YNS | E13: =IF(OR(A13="",B13=""),"",A13&"|"&B13) | F13: =IF(OR(E13="",C13=""),"",E13&"|"&C13)
... A775: Consola | B775: Autorizaciones | C775: Contraseña / PIN (escríbalo solo si el cliente lo proporciona) | D775: TXT | E775: =IF(OR(A775="",B775=""),"",A775&"|"&B775) | F775: =IF(OR(E775="",C775=""),"",E775&"|"&C775)
E776: =IF(OR(A776="",B776=""),"",A776&"|"&B776) | F776: =IF(OR(E776="",C776=""),"",E776&"|"&C776)
E777: =IF(OR(A777="",B777=""),"",A777&"|"&B777) | F777: =IF(OR(E777="",C777=""),"",E777&"|"&C777)
E778: =IF(OR(A778="",B778=""),"",A778&"|"&B778) | F778: =IF(OR(E778="",C778=""),"",E778&"|"&C778)
E779: =IF(OR(A779="",B779=""),"",A779&"|"&B779) | F779: =IF(OR(E779="",C779=""),"",E779&"|"&C779)
E780: =IF(OR(A780="",B780=""),"",A780&"|"&B780) | F780: =IF(OR(E780="",C780=""),"",E780&"|"&C780)
E781: =IF(OR(A781="",B781=""),"",A781&"|"&B781) | F781: =IF(OR(E781="",C781=""),"",E781&"|"&C781)
E782: =IF(OR(A782="",B782=""),"",A782&"|"&B782) | F782: =IF(OR(E782="",C782=""),"",E782&"|"&C782)
E783: =IF(OR(A783="",B783=""),"",A783&"|"&B783) | F783: =IF(OR(E783="",C783=""),"",E783&"|"&C783)
E784: =IF(OR(A784="",B784=""),"",A784&"|"&B784) | F784: =IF(OR(E784="",C784=""),"",E784&"|"&C784)
E785: =IF(OR(A785="",B785=""),"",A785&"|"&B785) | F785: =IF(OR(E785="",C785=""),"",E785&"|"&C785)
E786: =IF(OR(A786="",B786=""),"",A786&"|"&B786) | F786: =IF(OR(E786="",C786=""),"",E786&"|"&C786)
E787: =IF(OR(A787="",B787=""),"",A787&"|"&B787) | F787: =IF(OR(E787="",C787=""),"",E787&"|"&C787)
... E1000: =IF(OR(A1000="",B1000=""),"",A1000&"|"&B1000) | F1000: =IF(OR(E1000="",C1000=""),"",E1000&"|"&C1000)

Sheet Listas
A1: Tipo de equipo | B1: Clave | D1: Equipo | E1: Categoría / Falla | N1: L_YNC | O1: L_FUN | P1: L_FALLAP | Q1: L_DESDE | R1: L_PERM | S1: L_ENC | T1: L_OTRAF | U1: L_LUZ | V1: L_SENAL | W1: L_AUTON | X1: L_ZONAC | Y1: L_MANT | Z1: L_ABCE | AA1: L_ZONAI | AB1: L_ERR | AC1: L_PROG | AD1: L_SO | AE1: L_TEL | AF1: L_JUE | AG1: L_NCTRL | AH1: L_SOL | AI1: L_DANO | AJ1: L_CUANDO | AK1: L_MOM | AL1: L_LIQ | AM1: L_E_PANT | AN1: L_E_CARC | AO1: L_PIN | AP1: L_ANTIG | AQ1: L_USO | AR1: L_URG | AS1: L_CONT | AT1: L_BATED | AU1: L_CANT | AV1: L_CAID | AW1: L_DISCO | AX1: L_BATNIV | AY1: L_YN | AZ1: L_YNS | BA1: L_TXT
A2: Celular | B2: Celular | D2: Celular | E2: Datos generales | N2: Sí | O2: Funciona | P2: No enciende | Q2: Hoy | R2: Permanente | S2: Sí | T2: Ninguna | U2: Ninguna | V2: Ninguna | W2: Menos de 30 minutos | X2: Parte trasera | Y2: Nunca | Z2: Abierta | AA2: Pantalla | AB2: No aparece error | AC2: Todos por igual | AD2: Windows 11 | AE2: iPhone | AF2: Todos los discos | AG2: Ninguno | AH2: Ninguna | AI2: Ninguno | AJ2: Hoy | AK2: Uso normal | AL2: Agua | AM2: Sin daño | AN2: Buen estado | AO2: Proporcionó la contraseña | AP2: Menos de 6 meses | AQ2: Personal | AR2: Hoy mismo | AS2: WhatsApp | AT2: Menos de 1 año | AU2: Unas gotas | AV2: Una vez | AW2: HDD (mecánico) | AX2: Menos de 20% | AY2: Sí | AZ2: Sí | BA2: (escriba aquí)
A3: Reloj | B3: Reloj | D3: Celular | E3: No enciende | N3: No | O3: No funciona | P3: No carga / batería | Q3: Últimos 3 días | R3: Sucede algunas veces | S3: No | T3: Pantalla | U3: Roja | V3: Luz | W3: 30 min a 1 hora | X3: Parte superior | Y3: Menos de 6 meses | Z3: Cerrada | AA3: Esquina | AB3: Error de actualización | AC3: Navegador | AD3: Windows 10 | AE3: Android | AF3: Solo algunos | AG3: 1 | AH3: Reinició el equipo | AI3: Rayones leves | AJ3: Esta semana | AK3: Juegos | AL3: Agua de piscina | AM3: Rayones | AN3: Rayones | AO3: Cliente la ingresará en la prueba | AP3: 6 meses a 1 año | AQ3: Trabajo | AR3: En 2 o 3 días | AS3: Llamada | AT3: 1 a 2 años | AU3: Derrame pequeño | AV3: Varias veces | AW3: SSD | AX3: 20% a 50% | AY3: No | AZ3: No
A4: Computadora | B4: Computadora | D4: Celular | E4: Batería / No carga | N4: No fue posible comprobar | O4: No probado | P4: Pantalla dañada o sin imagen | Q4: Esta semana | R4: No sabe | S4: Intermitente | T4: Batería o carga | U4: Azul | V4: Vibración | W4: 1 a 3 horas | X4: Cerca de la batería | Y4: 6 a 12 meses | Z4: No sabe | AA4: Parte trasera | AB4: Error de disco | AC4: Juegos | AD4: Windows 7 o anterior | AE4: No sabe | AF4: Un solo disco | AG4: 2 | AH4: Cambió cargador o cable | AI4: Golpes | AJ4: Este mes | AK4: Cargando | AL4: Agua de mar | AM4: Quebrada | AN4: Golpes o abolladuras | AO4: No proporcionó contraseña | AP4: 1 a 2 años | AQ4: Estudio | AR4: Esta semana | AS4: Correo | AT4: 2 a 3 años | AU4: Derrame grande | AV4: No sabe | AW4: No sabe | AX4: 50% a 80% | AZ4: No sé
A5: Consola | B5: Consola | D5: Celular | E5: Calentamiento / Se apaga | P5: Se calienta o se apaga | Q5: Este mes | S5: No sé | T5: Sonido | U5: Blanca | V5: Sonido | W5: 3 a 6 horas | X5: Cerca de la cámara | Y5: Más de 1 año | AA5: Lateral | AB5: Error de red | AC5: Programas de trabajo | AD5: macOS | AF5: No aplica | AG5: 3 o más | AH5: Restableció de fábrica | AI5: Grietas | AJ5: Hace más de 1 mes | AK5: Siempre | AL5: Café | AM5: Manchas o líneas | AN5: Carcasa rota | AO5: No aplica | AP5: 2 a 4 años | AQ5: Personal y trabajo | AR5: Sin prisa | AS5: Pasará por el taller | AT5: Más de 3 años | AU5: Sumergido completamente | AX5: Más de 80%
D6: Celular | E6: Contacto con líquido | P6: Lentitud o se congela | Q6: Hace 1 a 3 meses | T6: Cámara | U6: Naranja | V6: Varias señales | W6: Más de 6 horas | X6: Todo el equipo | Y6: No sabe | AA6: Parte inferior | AB6: Error de hardware | AC6: Redes sociales / mensajería | AD6: Linux | AH6: Lo llevó a otro taller | AI6: Piezas sueltas | AJ6: No sabe | AL6: Gaseosa | AP6: Más de 4 años | AT6: No sabe | AU6: No sabe | AX6: No fue posible comprobar
D7: Celular | E7: Golpe / Caída | P7: Golpe o caída | Q7: Hace más de 3 meses | T7: Señal / Wi-Fi | U7: Verde | W7: No sabe | X7: No sabe | AA7: Parte superior | AB7: No sabe | AC7: Ninguno en específico | AD7: No sabe | AH7: Lo intentó reparar personalmente | AI7: Faltan piezas | AL7: Alcohol | AP7: No sabe
D8: Celular | E8: Pantalla / Imagen | P8: Contacto con líquido | Q8: No sabe | T8: Botones | U8: Parpadea | AA8: Varias zonas | AC8: Otro (ver Detalle) | AH8: Otra (ver Detalle) | AI8: Otro (ver Detalle) | AL8: Otro líquido
D9: Celular | E9: Lentitud / Sistema | P9: Sin sonido / cámara / micrófono | T9: Lentitud | AA9: No sabe
D10: Celular | E10: Cuenta / Bloqueo | P10: Sin señal o conexión | T10: Otra (ver Detalle)
D11: Celular | E11: Audio / Cámara / Micrófono | P11: Botones o teclado
D12: Celular | E12: Red / Señal / Conectividad | P12: Otra falla
D13: Celular | E13: Otra falla
D14: Celular | E14: Botones / Puertos
D15: Celular | E15: Software / Actualización
D16: Celular | E16: Estado físico
D17: Celular | E17: Estado al ingresar
D18: Celular | E18: Accesorios entregados
D19: Celular | E19: Fotografías de recepción
D20: Celular | E20: Pruebas funcionales de ingreso
D21: Celular | E21: Autorizaciones
D22: Reloj | E22: Datos generales
D23: Reloj | E23: No enciende
D24: Reloj | E24: Batería / No carga
... D86: Consola | E86: Autorizaciones
